flama/__init__.py
flama/applications.py
flama/asgi.py
flama/background.py
flama/client.py
flama/compat.py
flama/concurrency.py
flama/events.py
flama/exceptions.py
flama/http.py
flama/lifespan.py
flama/middleware.py
flama/modules.py
flama/negotiation.py
flama/py.typed
flama/sqlalchemy.py
flama/url.py
flama/validation.py
flama/websockets.py
flama/authentication/__init__.py
flama/authentication/components.py
flama/authentication/exceptions.py
flama/authentication/middleware.py
flama/authentication/types.py
flama/authentication/jwt/__init__.py
flama/authentication/jwt/algorithms.py
flama/authentication/jwt/claims.py
flama/authentication/jwt/jws.py
flama/authentication/jwt/jwt.py
flama/cli/__init__.py
flama/cli/__main__.py
flama/cli/commands/__init__.py
flama/cli/commands/model.py
flama/cli/commands/run.py
flama/cli/commands/serve.py
flama/cli/commands/start.py
flama/cli/config/__init__.py
flama/cli/config/app.py
flama/cli/config/config.py
flama/cli/config/uvicorn.py
flama/cli/templates/app.py.j2
flama/codecs/__init__.py
flama/codecs/base.py
flama/codecs/http/__init__.py
flama/codecs/http/jsondata.py
flama/codecs/http/multipart.py
flama/codecs/http/urlencoded.py
flama/codecs/websockets/__init__.py
flama/codecs/websockets/bytes.py
flama/codecs/websockets/json.py
flama/codecs/websockets/text.py
flama/config/__init__.py
flama/config/config.py
flama/config/data_structures.py
flama/config/exceptions.py
flama/config/fields.py
flama/config/loaders.py
flama/config/types.py
flama/ddd/__init__.py
flama/ddd/components.py
flama/ddd/exceptions.py
flama/ddd/repositories/__init__.py
flama/ddd/repositories/base.py
flama/ddd/repositories/http.py
flama/ddd/repositories/sqlalchemy.py
flama/ddd/workers/__init__.py
flama/ddd/workers/base.py
flama/ddd/workers/http.py
flama/ddd/workers/sqlalchemy.py
flama/ddd/workers/worker.py
flama/debug/__init__.py
flama/debug/data_structures.py
flama/debug/middleware.py
flama/debug/types.py
flama/endpoints/__init__.py
flama/endpoints/base.py
flama-1.11.7.dist-info/METADATA
flama-1.11.7.dist-info/WHEEL
flama-1.11.7.dist-info/entry_points.txt
flama-1.11.7.dist-info/licenses/LICENSE
flama-1.11.7.dist-info/RECORD
