Metadata-Version: 2.4
Name: flama
Version: 1.11.7
Summary: Fire up your models with the flame 🔥
Project-URL: repository, https://github.com/vortico/flama
Project-URL: homepage, https://flama.dev
Project-URL: documentation, https://flama.dev/docs/
Author-email: José Antonio Perdiguero López <perdy@perdy.io>, "Miguel A. Durán Olivencia" <migduroli@gmail.com>
Maintainer-email: José Antonio Perdiguero López <perdy@perdy.io>, "Miguel A. Durán Olivencia" <migduroli@gmail.com>
License: Apache-2.0
License-File: LICENSE
Keywords: api,machine-learning,ml,ml-ops,mlops,openapi,pytorch,rest,restful,sklearn,tensorflow
Classifier: Development Status :: 5 - Production/Stable
Classifier: Intended Audience :: Developers
Classifier: Topic :: Internet :: WWW/HTTP :: HTTP Servers
Classifier: Topic :: Software Development
Classifier: Topic :: Software Development :: Libraries
Classifier: Topic :: Software Development :: Libraries :: Application Frameworks
Requires-Python: <3.14,>=3.9
Requires-Dist: click<9.0,>=8.1
Requires-Dist: jinja2<4.0,>=3.1.2
Requires-Dist: pyyaml<7.0,>=6.0
Requires-Dist: starlette<1.0.0,>=0.31
Requires-Dist: typing-extensions<5.0,>=4.4; python_version < '3.10'
Requires-Dist: uvicorn[standard]<1.0.0,>=0.23
Provides-Extra: client
Requires-Dist: httpx<1.0,>=0.25; extra == 'client'
Provides-Extra: database
Requires-Dist: sqlalchemy[asyncio]<3.0,>=2.0; extra == 'database'
Provides-Extra: full
Requires-Dist: apispec<7.0,>=6.0; extra == 'full'
Requires-Dist: httpx<1.0,>=0.25; extra == 'full'
Requires-Dist: marshmallow<4.0,>=3.0; extra == 'full'
Requires-Dist: pydantic<3.0,>=2.0; extra == 'full'
Requires-Dist: sqlalchemy[asyncio]<3.0,>=2.0; extra == 'full'
Requires-Dist: typesystem<1.0,>=0.4.1; extra == 'full'
Provides-Extra: marshmallow
Requires-Dist: apispec<7.0,>=6.0; extra == 'marshmallow'
Requires-Dist: marshmallow<4.0,>=3.0; extra == 'marshmallow'
Provides-Extra: pydantic
Requires-Dist: pydantic<3.0,>=2.0; extra == 'pydantic'
Provides-Extra: typesystem
Requires-Dist: typesystem<1.0,>=0.4.1; extra == 'typesystem'
